hxapy/__init__.py
hxapy/hxa.py
hxapy/tests.py
hxapy-0.0.12.dist-info/METADATA
hxapy-0.0.12.dist-info/WHEEL
hxapy-0.0.12.dist-info/licenses/LICENSE
hxapy-0.0.12.dist-info/RECORD
