Metadata-Version: 2.1
Name: hxapy
Version: 0.0.12
Summary: A hxa library for python
Project-URL: Homepage, https://github.com/shmoich/hxapy
Author-email: Riles Leroy <rilesleroy@gmail.com>
License: MIT License
Classifier: License :: OSI Approved :: MIT License
Classifier: Operating System :: OS Independent
Classifier: Programming Language :: Python :: 3
Requires-Python: >=3.7
